ff21003/__init__.py
ff21003/biseccion.py
ff21003/crammer.py
ff21003/descomposicion_lu.py
ff21003/eliminacion_gauss.py
ff21003/gauss_jordan.py
ff21003/gauss_seidel.py
ff21003/jacobi.py
ff21003uno-0.0.2.dist-info/METADATA
ff21003uno-0.0.2.dist-info/WHEEL
ff21003uno-0.0.2.dist-info/top_level.txt
ff21003uno-0.0.2.dist-info/RECORD
