Metadata-Version: 2.4
Name: FF21003UNO
Version: 0.0.2
Summary: Librería para resolver sistemas de ecuaciones lineales y no lineales
Home-page: https://github.com/ff21003/FF21003UNO
Author: Sofia Franco
Author-email: ff21003@ues.edu.sv
License: MIT
Requires-Dist: numpy
Requires-Dist: scipy
Dynamic: author
Dynamic: author-email
Dynamic: description
Dynamic: description-content-type
Dynamic: home-page
Dynamic: license
Dynamic: requires-dist
Dynamic: summary
